rotalabs_ftms/__init__.py
rotalabs_ftms-0.0.1.dist-info/METADATA
rotalabs_ftms-0.0.1.dist-info/WHEEL
rotalabs_ftms-0.0.1.dist-info/RECORD
