Metadata-Version: 2.4
Name: rotalabs-ftms
Version: 0.0.1
Summary: Field-theoretic memory for AI agents - Continuous field representation with natural decay
Project-URL: Homepage, https://rotalabs.ai
Project-URL: Repository, https://github.com/rotalabs/rotalabs-ftms
Author-email: Rotalabs <research@rotalabs.ai>
License-Expression: MIT
Keywords: agents,ai,field-theory,machine-learning,memory
Classifier: Development Status :: 1 - Planning
Classifier: Intended Audience :: Developers
Classifier: Intended Audience :: Science/Research
Classifier: License :: OSI Approved :: MIT License
Classifier: Programming Language :: Python :: 3
Classifier: Topic :: Scientific/Engineering :: Artificial Intelligence
Requires-Python: >=3.9
